sapy5/__init__.py
sapy5/main.py
sapy5-1.0.0.0.dist-info/LICENSE
sapy5-1.0.0.0.dist-info/METADATA
sapy5-1.0.0.0.dist-info/WHEEL
sapy5-1.0.0.0.dist-info/top_level.txt
sapy5-1.0.0.0.dist-info/RECORD
