Metadata-Version: 2.1
Name: sapy5
Version: 1.0.0.0
Summary: Makes it easy to use sapi from Python.
Home-page: https://twitter.com/Rilm2525
Author: Rilm2525
Author-email: rilm2525ce@gmail.com
License: MIT
License-File: LICENSE
Requires-Dist: pywin32
